LICENSE
README.md
nseekfs-1.0.4.dist-info/METADATA
nseekfs-1.0.4.dist-info/WHEEL
nseekfs-1.0.4.dist-info/entry_points.txt
nseekfs-1.0.4.dist-info/licenses/LICENSE
nseekfs/__init__.py
nseekfs/highlevel.py
nseekfs/nseekfs.abi3.so
nseekfs-1.0.4.dist-info/RECORD
