Metadata-Version: 2.4
Name: nseekfs
Version: 1.0.4
Classifier: Development Status :: 5 - Production/Stable
Classifier: Intended Audience :: Developers
Classifier: Intended Audience :: Science/Research
Classifier: License :: OSI Approved :: MIT License
Classifier: Operating System :: OS Independent
Classifier: Programming Language :: Python :: 3
Classifier: Programming Language :: Python :: 3.8
Classifier: Programming Language :: Python :: 3.9
Classifier: Programming Language :: Python :: 3.10
Classifier: Programming Language :: Python :: 3.11
Classifier: Programming Language :: Python :: 3.12
Classifier: Programming Language :: Rust
Classifier: Topic :: Scientific/Engineering :: Artificial Intelligence
Classifier: Topic :: Software Development :: Libraries :: Python Modules
Classifier: Typing :: Typed
Requires-Dist: numpy>=1.19.0
Requires-Dist: pytest>=6.0 ; extra == 'dev'
Requires-Dist: pytest-benchmark>=3.4.1 ; extra == 'dev'
Requires-Dist: black>=22.0 ; extra == 'dev'
Requires-Dist: ruff>=0.0.200 ; extra == 'dev'
Requires-Dist: mypy>=0.991 ; extra == 'dev'
Requires-Dist: scipy>=1.7.0 ; extra == 'analysis'
Requires-Dist: scikit-learn>=1.0.0 ; extra == 'analysis'
Requires-Dist: pandas>=1.3.0 ; extra == 'analysis'
Requires-Dist: matplotlib>=3.3.0 ; extra == 'analysis'
Requires-Dist: seaborn>=0.11.0 ; extra == 'analysis'
Requires-Dist: psutil>=5.8.0 ; extra == 'profiling'
Requires-Dist: memory-profiler>=0.60.0 ; extra == 'profiling'
Requires-Dist: line-profiler>=3.3.0 ; extra == 'profiling'
Requires-Dist: py-spy>=0.3.12 ; extra == 'profiling'
Requires-Dist: nseekfs[dev,analysis,profiling] ; extra == 'all'
Provides-Extra: dev
Provides-Extra: analysis
Provides-Extra: profiling
Provides-Extra: all
License-File: LICENSE
Summary: High-performance exact vector similarity search with Rust backend
Keywords: vector,similarity,search,rust,machine-learning,embeddings
Author-email: Diogo Novo <contact@nseek.io>
Maintainer-email: Diogo Novo <contact@nseek.io>
License: MIT
Requires-Python: >=3.8
Project-URL: Homepage, https://github.com/NSeek-AI/nseekfs
Project-URL: Documentation, https://github.com/NSeek-AI/nseekfs/wiki
Project-URL: Repository, https://github.com/NSeek-AI/nseekfs.git
